{
  "project_info": {
    "project_number": "749970755954",
    "project_id": "db-shopping-f512a",
    "storage_bucket": "db-shopping-f512a.appspot.com"
  },
  "client": [
    {
      "client_info": {
        "mobilesdk_app_id": "1:749970755954:android:f76ed462c755ad58fb0deb",
        "android_client_info": {
          "package_name": "com.example.dbshopping"
        }
      },
      "oauth_client": [],
      "api_key": [
        {
          "current_key": "AIzaSyDLosYd2DJMrMZ33PQX8gXJR-h8tTcVanU"
        }
      ],
      "services": {
        "appinvite_service": {
          "other_platform_oauth_client": []
        }
      }
    }
  ],
  "configuration_version": "1"
}